vault/__init__.py
vault/__main__.py
vault/vault.py
vault/lib/Config.py
vault/lib/Encryption.py
vault/lib/__init__.py
vault/models/Category.py
vault/models/Secret.py
vault/models/User.py
vault/models/__init__.py
vault/models/base.py
vault/modules/__init__.py
vault/modules/autocomplete.py
vault/modules/carry.py
vault/modules/misc.py
vault/views/__init__.py
vault/views/categories.py
vault/views/change_key.py
vault/views/clipboard.py
vault/views/import_export.py
vault/views/menu.py
vault/views/migration.py
vault/views/secrets.py
vault/views/setup.py
vault/views/users.py
pyvault-2.4.5.dist-info/LICENSE
pyvault-2.4.5.dist-info/METADATA
pyvault-2.4.5.dist-info/WHEEL
pyvault-2.4.5.dist-info/entry_points.txt
pyvault-2.4.5.dist-info/top_level.txt
pyvault-2.4.5.dist-info/RECORD
