Metadata-Version: 2.1
Name: pyvault
Version: 2.4.5
Summary: Python password manager
Home-page: https://github.com/gabfl/vault
Author: Gabriel Bordeaux
Author-email: pypi@gab.lc
License: MIT
Classifier: Topic :: Security
Classifier: Topic :: Security :: Cryptography
Classifier: License :: OSI Approved :: MIT License
Classifier: Operating System :: MacOS
Classifier: Operating System :: POSIX :: Linux
Classifier: Natural Language :: English
Classifier: Programming Language :: Python :: 3
Classifier: Programming Language :: Python
Classifier: Development Status :: 4 - Beta
License-File: LICENSE
Requires-Dist: pycryptodome==3.20.0
Requires-Dist: pyperclip
Requires-Dist: tabulate
Requires-Dist: passwordgenerator
Requires-Dist: SQLAlchemy==1.4.41
Requires-Dist: sqlcipher3==0.5.3
